autonis/__init__.py
autonis-1.0.1.dist-info/LICENSE.txt
autonis-1.0.1.dist-info/METADATA
autonis-1.0.1.dist-info/WHEEL
autonis-1.0.1.dist-info/top_level.txt
autonis-1.0.1.dist-info/RECORD
