Metadata-Version: 2.1
Name: autonis
Version: 1.0.1
Summary: A Python package help you to automate your web easily using python program
Home-page: UNKNOWN
Author: Void
License: MIT
Platform: UNKNOWN
Classifier: License :: OSI Approved :: MIT License
Requires-Python: >=3.6
Requires-Dist: urllib3
Requires-Dist: wikipedia
Requires-Dist: requests
Requires-Dist: bs4
Requires-Dist: speedtest-cli
